githon/__init__.py
githon/exceptions.py
githon/github.py
githon/repository.py
githon/utils.py
githon-0.7.0.dist-info/DESCRIPTION.rst
githon-0.7.0.dist-info/METADATA
githon-0.7.0.dist-info/RECORD
githon-0.7.0.dist-info/WHEEL
githon-0.7.0.dist-info/metadata.json
githon-0.7.0.dist-info/top_level.txt
