Metadata-Version: 2.0
Name: githon
Version: 0.7.0
Summary: A simple Data Scraping library for GitHub REST API v3
Home-page: https://github.com/marcosvbras/githon
Author: Marcos Vinícius Brás
Author-email: marcosvbras@gmail.com
License: Apache
Download-URL: https://github.com/marcosvbras/githon
Keywords: data github scraping api
Platform: UNKNOWN
Classifier: Development Status :: 4 - Beta
Classifier: Environment :: Web Environment
Classifier: Intended Audience :: Developers
Classifier: License :: OSI Approved :: Apache Software License
Classifier: Natural Language :: English
Classifier: Operating System :: OS Independent
Classifier: Programming Language :: Python :: 3.4
Classifier: Programming Language :: Python :: 3.5
Classifier: Topic :: Internet
Classifier: Topic :: Software Development :: Libraries :: Python Modules
Requires-Python: ~=3.3
Requires-Dist: certifi (==2017.7.27.1)
Requires-Dist: chardet (==3.0.4)
Requires-Dist: idna (==2.6)
Requires-Dist: python-dateutil (==2.6.1)
Requires-Dist: requests (==2.18.4)
Requires-Dist: six (==1.11.0)
Requires-Dist: urllib3 (==1.22)
